AccelBrainBeat/__init__.py
AccelBrainBeat/brain_beat.py
AccelBrainBeat/brainbeat/__init__.py
AccelBrainBeat/brainbeat/binaural_beat.py
AccelBrainBeat/brainbeat/monaural_beat.py
AccelBrainBeat/waveform/__init__.py
AccelBrainBeat/waveform/sine_wave.py
AccelBrainBeat/waveform/interface/__init__.py
AccelBrainBeat/waveform/interface/wave_form_interface.py
AccelBrainBeat-1.0.5.dist-info/DESCRIPTION.rst
AccelBrainBeat-1.0.5.dist-info/METADATA
AccelBrainBeat-1.0.5.dist-info/RECORD
AccelBrainBeat-1.0.5.dist-info/WHEEL
AccelBrainBeat-1.0.5.dist-info/metadata.json
AccelBrainBeat-1.0.5.dist-info/top_level.txt
