Metadata-Version: 2.0
Name: AccelBrainBeat
Version: 1.0.5
Summary: AccelBrainBeat is a Python library for creating the binaural beats or monaural beats. You can play these beats and generate wav files. The frequencys can be optionally selected.
Home-page: https://github.com/chimera0/accel-brain-code/tree/master/Binaural-Beat-and-Monaural-Beat-with-python
Author: chimera0
Author-email: ai-brain-lab@accel-brain.com
License: GPL2
Keywords: binaural monaural beats brain wave wav audio
Platform: UNKNOWN
Classifier: Development Status :: 5 - Production/Stable
Classifier: Intended Audience :: Developers
Classifier: Intended Audience :: Science/Research
Classifier: Intended Audience :: Healthcare Industry
Classifier: Topic :: Multimedia :: Sound/Audio
Classifier: Topic :: Scientific/Engineering :: Medical Science Apps.
Classifier: License :: OSI Approved :: GNU General Public License (GPL)
Classifier: Programming Language :: Python :: 3
Requires-Dist: numpy
